{
  "DYJetsToLL": {
    "M10to50": 5075.3797,
    "M50": 34451.2441
  },
  "QCD_EMEnriched": {
    "15to20": 5.9667,
    "20to30": 2.9266,
    "30to50": 1.33,
    "50to80": 5.2803,
    "80to120": 25.7643,
    "120to170": 145.3357,
    "170to300": 223.5043,
    "300toInf": 2007.2409
  },
  "QCD_MuEnriched": {
    "20to30": 23.893,
    "30to50": 42.9055,
    "50to80": 105.8795,
    "80to120": 508.7147,
    "120to170": 1802.8541,
    "170to300": 10265.8155,
    "300to470": 95249.2422,
    "470to600": 656872.1558,
    "600to800": 2060827.8116,
    "800to1000": 24060650.1067
  },
  "SingleTop": {
    "s-channel_LeptonDecays": 5178074.5989,
    "t-channel_AntiTop_InclusiveDecays": 1407728.5441,
    "t-channel_Top_InclusiveDecays": 1558659.612,
    "tW_AntiTop_InclusiceDecays": 238357.4285,
    "tW_Top_InclusiveDecays": 245177.1957
  },
  "TTBar": {
    "TTTo2L2Nu": 1642541.6242,
    "TTToSemiLeptonic": 1304012.7005
  },
  "TTW": {
    "TTWToLNu": 48514391.8292
  },
  "TTZ": {
    "TTZToLL": 393271344.4028
  },
  "Rare": {
    "THQ": 93446130.4484,
    "THW": 98902195.6088,
    "TTHH": 751314800.9016,
    "TTTJ": 1258178158.0272,
    "TTTT": 1589918422.0139,
    "TTTW": 672841187.6873,
    "TTWH": 435582822.0859,
    "TTWW": 134953538.2416,
    "TTWZ": 203431372.549,
    "TTZH": 442869796.2799,
    "TTZZ": 359307359.3074,
    "tZq_ll": 12649681.5287
  },
  "HTbinnedWJets": {
    "Inclusive": 1516.3942,
    "70to100": 52100.9095,
    "100to200": 41127.1736,
    "200to400": 172265.1834,
    "400to600": 163821.0827,
    "600to800": 708793.8476,
    "800to1200": 1481985.1927,
    "1200to2500": 5602003.4572,
    "2500toInf": 793962149.8865
  },
  "WJetsNLO": {
    "Inclusive": 434.919,
    "100to250": 638576.8375,
    "250to400": 3766807.7709,
    "400to600": 3495193.2939,
    "600toInf": 6941887.5278
  },
  "WGamma": {
    "WGToLnuG_01J": 70107.0552
  },
  "ZGamma": {
    "ZGToLLG_01J": 592588.5918
  },
  "WW": {
    "WWTo1L1Nu2Q": 787485.5886,
    "WWTo2L2Nu": 901172.2272,
    "WWTo4Q": 773049.8534
  },
  "WpWp": {
    "WpWpJJEWK": 3041362.5304,
    "WpWpJJQCD": 6313131.3131
  },
  "WZ": {
    "WZTo1L1Nu2Q": 805257.7308,
    "WZTo2Q2L": 4499605.7314,
    "WZTo3LNu": 1889798.5376
  },
  "ZZ": {
    "ZZTo2L2Nu": 56787841.4459,
    "ZZTo2Q2L": 7928149.6084,
    "ZZTo2Q2Nu": 4405016.4518,
    "ZZTo4L": 74330566.0377
  },
  "WWW": {
    "Inclusive": 1112140.8712
  },
  "WWZ": {
    "Inclusive": 1452841.2419
  },
  "WZZ": {
    "Inclusive": 5254860.7462
  },
  "ZZZ": {
    "Inclusive": 16937669.3767
  },
  "Higgs": {
    "bbH_HToZZTo4L": 3533384497.3139,
    "GluGluHToZZTo4L": 28693528693.5287,
    "GluGluToZH": 75554356.2066,
    "GluGluZH": 344444108.7613,
    "ttHToNonbb": 34603366.3834,
    "VBF_HToZZTo4L": 472277227.7228,
    "VHToNonbb": 13166481.4209
  },
  "SingleMuon": {
    "SingleMuon_A": 59830,
    "SingleMuon_B": 59830,
    "SingleMuon_C": 59830,
    "SingleMuon_D": 59830
  },
  "EGamma": {
    "EGamma_A": 59830,
    "EGamma_B": 59830,
    "EGamma_C": 59830,
    "EGamma_D": 59830
  }
}